abi_parser/__init__.py
abiparser/__init__.py
abiparser-1.0.1.dist-info/METADATA
abiparser-1.0.1.dist-info/WHEEL
abiparser-1.0.1.dist-info/top_level.txt
abiparser-1.0.1.dist-info/RECORD
