Metadata-Version: 2.1
Name: abiparser
Version: 1.0.1
Summary: A Python package to parse Ethereum contract ABI files
Author: August Radjoe
Author-email: atg271@gmail.com
